{  "project_info": {    "project_number": "745882748124",    "firebase_url": "https://flutter-interview-18a7e.firebaseio.com",    "project_id": "flutter-interview-18a7e",    "storage_bucket": "flutter-interview-18a7e.appspot.com"  },  "client": [    {      "client_info": {        "mobilesdk_app_id": "1:745882748124:android:e3d93b96164e70216de019",        "android_client_info": {          "package_name": "com.interview.flutter_interview"        }      },      "oauth_client": [        {          "client_id": "745882748124-bn5os3p5upb2rn1cg8e9s6k0e8p91r75.apps.googleusercontent.com",          "client_type": 3        }      ],      "api_key": [        {          "current_key": "AIzaSyATgndDkDufQg3vOEBpxmFBPvdtaw656H4"        }      ],      "services": {        "appinvite_service": {          "other_platform_oauth_client": [            {              "client_id": "745882748124-bn5os3p5upb2rn1cg8e9s6k0e8p91r75.apps.googleusercontent.com",              "client_type": 3            }          ]        }      }    }  ],  "configuration_version": "1"}